fml_manager/__init__.py
fml_manager/fml_cluster_manager.py
fml_manager/fml_manager.py
fml_manager/utils/__init__.py
fml_manager/utils/core.py
fml_manager/utils/fate_builders.py
fml_manager/utils/file_utils.py
fml_manager/utils/fmt_obj.py
fml_manager-0.5.0.dist-info/LICENSE
fml_manager-0.5.0.dist-info/METADATA
fml_manager-0.5.0.dist-info/WHEEL
fml_manager-0.5.0.dist-info/top_level.txt
fml_manager-0.5.0.dist-info/RECORD
