Metadata-Version: 2.1
Name: fml-manager
Version: 0.5.0
Summary: Python client for FATE cluster
Home-page: https://not-decided.yet
Author: Layne Peng/Jiahao Chen
Author-email: jiahaoc@vmware.com
License: UNKNOWN
Platform: UNKNOWN
Classifier: Programming Language :: Python :: 3
Classifier: License :: OSI Approved :: Apache Software License
Classifier: Operating System :: OS Independent
Requires-Python: >=3.6
Requires-Dist: cachetools (==3.0.0)
Requires-Dist: requests (>=2.21.0)
Requires-Dist: pandas (>=1.1.0)
